pigeons/__init__.py
pigeons/dispatcher.py
pigeons/filter.py
tests/__init__.py
tests/test_dispatcher.py
tests/test_filter.py
pigeons-0.0.4.dist-info/LICENSE
pigeons-0.0.4.dist-info/METADATA
pigeons-0.0.4.dist-info/WHEEL
pigeons-0.0.4.dist-info/top_level.txt
pigeons-0.0.4.dist-info/RECORD
