Metadata-Version: 2.1
Name: pigeons
Version: 0.0.4
Summary: Handy logging tool to send logs to MSTeams with or without filters.
Home-page: https://github.com/obss/pigeons
Author: 
License: MIT
Platform: UNKNOWN
Classifier: Programming Language :: Python :: 3.6
Classifier: Programming Language :: Python :: 3.7
Classifier: Programming Language :: Python :: 3.8
Classifier: Programming Language :: Python :: 3.9
Classifier: License :: OSI Approved :: MIT License
Classifier: Operating System :: OS Independent
Classifier: Topic :: Utilities
Classifier: Topic :: Software Development :: Libraries :: Python Modules
Requires-Python: >=3.6
Requires-Dist: requests (==2.25.1)
Requires-Dist: teams-logger (==0.4.0)
Requires-Dist: validators (==0.18.2)
